slang/__init__.py
slang/chunkers.py
slang/core.py
slang/featurizers.py
slang/snip_stats.py
slang/snippers.py
slang/spectrop.py
slang/stypes.py
slang/util.py
slang/util_data.py
slang/scrap/__init__.py
slang/scrap/learning_pipeline_01.py
slang/scrap/scrap_01.py
slang/scrap/the_apis_i_wish_for.py
slang-0.0.7.dist-info/LICENSE
slang-0.0.7.dist-info/METADATA
slang-0.0.7.dist-info/WHEEL
slang-0.0.7.dist-info/top_level.txt
slang-0.0.7.dist-info/RECORD
